examy/__init__.py
examy/fetchers/new_web_layout/kiss.py
examy/fetchers/new_web_layout/optimized.py
examy/fetchers/new_web_layout/utils/process_html.py
examy/fetchers/new_web_layout/utils/webpage_actions.py
examy/models/ExamDescriptor.py
examy/models/ExamReport.py
examy/models/Ranking.py
examy/models/Student.py
examy/models/Test.py
examy/models/TestResult.py
examy/models/exceptions.py
examy/models/fetcher.py
examy/utils/__init__.py
examy/utils/export.py
examy/utils/manager.py
examy/utils/stgroup.py
examy-0.1.15.dist-info/LICENSE
examy-0.1.15.dist-info/METADATA
examy-0.1.15.dist-info/WHEEL
examy-0.1.15.dist-info/RECORD
